gbk_diy_github_files/__init__.py
gbk_diy_github_files/core.py
gbk_diy_github_files/main.py
gbk_diy_github_files-0.1.2.dist-info/METADATA
gbk_diy_github_files-0.1.2.dist-info/WHEEL
gbk_diy_github_files-0.1.2.dist-info/entry_points.txt
gbk_diy_github_files-0.1.2.dist-info/licenses/LICENSE
gbk_diy_github_files-0.1.2.dist-info/RECORD
