Metadata-Version: 2.4
Name: gbk-diy-github-files
Version: 0.1.2
Summary: 一个通过GitHub仓库URL快速创建标准项目文件夹结构的CLI工具。
Author-email: wanderer <gbk2667503771@gmail.com>
License: MIT License
License-File: LICENSE
Classifier: Environment :: Console
Classifier: License :: OSI Approved :: MIT License
Classifier: Operating System :: OS Independent
Classifier: Programming Language :: Python :: 3
Classifier: Topic :: Utilities
Requires-Python: >=3.8
Requires-Dist: typer[all]>=0.9.0
Requires-Dist: typing-extensions
Provides-Extra: dev
Requires-Dist: mypy; extra == 'dev'
Requires-Dist: pre-commit; extra == 'dev'
Requires-Dist: pytest; extra == 'dev'
Requires-Dist: pytest-cov; extra == 'dev'
Requires-Dist: ruff; extra == 'dev'
